README.md
setup.cfg
setup.py
letslog/__init__.py
letslog.egg-info/PKG-INFO
letslog.egg-info/SOURCES.txt
letslog.egg-info/dependency_links.txt
letslog.egg-info/requires.txt
letslog.egg-info/top_level.txt