Metadata-Version: 2.1
Name: letslog
Version: 0.0.5
Summary: A logger package
Home-page: https://github.com/yifeili98/letslog
Author: YiFei Li
Author-email: yifeil@berkeley.edu
License: MIT
Download-URL: https://github.com/yifeili98/letslog/archive/0.0.5.tar.gz
Platform: UNKNOWN
Classifier: Programming Language :: Python :: 3
Classifier: Operating System :: OS Independent
